<?xml version="1.0" encoding="UTF-8" standalone="no" ?><CAERep ObjId="52" Type="CAERep" Ver="2"><CapabilityId PropType="string">Rakesh-kumar-iitk-6-janga-13244-002777</CapabilityId><DSEnvironmentID PropType="int">36</DSEnvironmentID><ExternalProductVersion PropType="string">2021 R1</ExternalProductVersion><Goal PropType="string">WriteCAERep</Goal><HasBetaKeyOn PropType="bool">false</HasBetaKeyOn><InProcess PropType="bool">true</InProcess><LastDatabaseId PropType="unsigned int">73</LastDatabaseId><LicenseServer PropType="string">60244@Rakesh-kumar-iitk-6</LicenseServer><NumProcessorsForPost PropType="int">0</NumProcessorsForPost><PID_Legacy_Solve PropType="int">0</PID_Legacy_Solve><PartialCode PropType="int">1</PartialCode><ProductVersion PropType="string">21.1 RELEASE</ProductVersion><ProductVersionForSec PropType="string">21.1</ProductVersionForSec><ProjectName PropType="string">wbnew--Topology Optimization (B5)</ProjectName><ReturnCode PropType="int">1</ReturnCode><SolveInvokedFromAddin PropType="int">0</SolveInvokedFromAddin><SysvarMap PropType="map&lt;string,string>"><Entry key="DSSolver ProgId">AMKSolver.AMKSolver.211</Entry><Entry key="full ansys">ansys</Entry></SysvarMap><EngineeringRep ObjId="53" Type="EngineeringRep" Ver="2"><BCRep ObjId="56" Type="BCRep" Ver="2"><OptimizationRegionRep ObjId="39" Type="OptimizationRegionRep" Ver="1"><AdditionalScopingCount PropType="unsigned int">2</AdditionalScopingCount><Caption PropType="string">Optimization Region</Caption><LatticeType PropType="string"> </LatticeType><MaxDensity PropType="double">   -1</MaxDensity><MinDensity PropType="double">   -1</MinDensity><OptimizationType PropType="string">kOptimizationTypeTopology</OptimizationType><ScopingSubset0 PropType="vector&lt;string>">40</ScopingSubset0><ScopingSubset1 PropType="vector&lt;string>">-1</ScopingSubset1><ScopingSubset2 PropType="vector&lt;string>">29</ScopingSubset2><ScopingSubset3 PropType="vector&lt;string>">31</ScopingSubset3></OptimizationRegionRep><TopoConstraintRep ObjId="42" Type="TopoConstraintRep" Ver="4"><Caption PropType="string">Mass Constraint_42</Caption><EnvironmentSelectionId PropType="unsigned int">0</EnvironmentSelectionId><ManuConstraintSubType PropType="string"> </ManuConstraintSubType><MaxMemberSizeControlledType PropType="string"> </MaxMemberSizeControlledType><MinMemberSizeControlledType PropType="string"> </MinMemberSizeControlledType><NumberOfSteps PropType="unsigned int">0</NumberOfSteps><Percentage PropType="double">   60</Percentage><PercentageMaximum PropType="unsigned int">50</PercentageMaximum><PercentageMinimum PropType="unsigned int">50</PercentageMinimum><ResponseConstraintDefineBy PropType="string">kDSResponseConstraintDefineByConstant</ResponseConstraintDefineBy><ResponseConstraintType PropType="string">kDSResponseConstraintTypeMass</ResponseConstraintType><TopoConstraintType PropType="string">kDSResponseConstraintType</TopoConstraintType></TopoConstraintRep><TopoObjectiveRep ObjId="41" Type="TopoObjectiveRep" Ver="4"><Caption PropType="string">Objective</Caption><CriterionIDs PropType="vector&lt;int>">0</CriterionIDs><EndModes PropType="vector&lt;int>">-1</EndModes><EndSteps PropType="vector&lt;int>">1</EndSteps><EnvironmentIDs PropType="vector&lt;int>">22</EnvironmentIDs><EnvironmentTypes PropType="vector&lt;int>">-1</EnvironmentTypes><Formulation PropType="string"/><Goal PropType="string"/><LoadCasesInUse PropType="int">1</LoadCasesInUse><Modes PropType="vector&lt;int>">-1</Modes><MultipleFomulations PropType="vector&lt;string>">kFormulationProgramControlled</MultipleFomulations><MultipleGoals PropType="vector&lt;string>">kGoalMinimize</MultipleGoals><MultipleResponseTypes PropType="vector&lt;string>">kReponseTypeCompliance</MultipleResponseTypes><NormalizedSum PropType="string">false</NormalizedSum><NumSteps PropType="vector&lt;int>">1</NumSteps><ResponseType PropType="string"/><SingleSets PropType="vector&lt;bool>">false</SingleSets><StartModes PropType="vector&lt;int>">-1</StartModes><StartSteps PropType="vector&lt;int>">1</StartSteps><Step PropType="vector&lt;int>">-1</Step><Weights PropType="vector&lt;double>">    1</Weights></TopoObjectiveRep><TopoOptDependencyEnvRep ObjId="71" Type="TopoOptDependencyEnvRep" Ver="1"><Caption PropType="string">Static Structural</Caption><EnvironmentAnalysisType PropType="int">0</EnvironmentAnalysisType><EnvironmentId PropType="unsigned int">22</EnvironmentId><EnvironmentPhysicsType PropType="int">1</EnvironmentPhysicsType><EnvironmentSolverFilesDirectory PropType="string">C:\Users\janga\AppData\Local\Temp\WB_janga_13636_2\wbnew_files\dp0\SYS\MECH\</EnvironmentSolverFilesDirectory><EnvironmentTimeSteps PropType="vector&lt;double>" UCat="Time" Unt="s">    1</EnvironmentTimeSteps><IsThermalImportedLoadPresent PropType="bool">false</IsThermalImportedLoadPresent><SolverUnitsId PropType="int">6</SolverUnitsId></TopoOptDependencyEnvRep></BCRep><GeometryAttributes ObjId="54" Type="GeometryAttributes" Ver="2"><AssemblyAttributes ObjId="55" Type="AssemblyAttributes" Ver="2"><ElementOptionControl PropType="string">ProgramControlled</ElementOptionControl><GeometrySource PropType="string">C:\Users\janga\AppData\Local\Temp\WB_janga_13636_2\wbnew_files\dp0\SYS\DM\SYS.scdoc</GeometrySource><Is2DAnalysis PropType="bool">false</Is2DAnalysis><IsMixedDimension PropType="bool">false</IsMixedDimension><PartAttributes ObjId="17" Type="PartAttributes" Ver="2"><Caption PropType="string">SYS Bodies</Caption><Mass PropType="double" UCat="Mass" Unt="tonne">4.371768354924016e-06</Mass><PartId PropType="unsigned int">3</PartId><BodyAttributes ObjId="18" Type="BodyAttributes" Ver="2"><AreNonLinearEffectsOn PropType="bool">true</AreNonLinearEffectsOn><BoundingBoxDiagonal PropType="double" UCat="Length" Unt="mm">31.34348267666947</BoundingBoxDiagonal><Caption PropType="string">SYS\Solid</Caption><ElementCoordSysId PropType="unsigned int">21</ElementCoordSysId><GeometryType PropType="string">Solid</GeometryType><Mass PropType="double" UCat="Mass" Unt="tonne">4.371768354924016e-06</Mass><ProtoReferenceId PropType="unsigned int">13</ProtoReferenceId><StiffnessBehavior PropType="string">Deformable</StiffnessBehavior><ThermalStrainCalculation PropType="bool">true</ThermalStrainCalculation><Centroid ObjId="63" Type="DSGePoint3d" Ver="3"><Coordinates PropType="vector&lt;double>" UCat="Length" Unt="mm">-20.32239059978147,1.000000047497351,-6.712913236912678</Coordinates></Centroid><MassMomentOfInertia ObjId="62" Type="MassMomentOfInertia" Ver="2"><Ixx PropType="double" UCat="MomentInertiaMass" Unt="tonne mm^2">6.075013844705717e-05</Ixx><Iyy PropType="double" UCat="MomentInertiaMass" Unt="tonne mm^2">0.000264933137723664</Iyy><Izz PropType="double" UCat="MomentInertiaMass" Unt="tonne mm^2">0.000207097378205888</Izz></MassMomentOfInertia><MaterialRep ObjId="61" Type="MaterialRep" Ver="2"><MaterialName PropType="string">Structural Steel</MaterialName><ReferenceTemperature PropType="double" UCat="Temperature" Unt="Celsius">   22</ReferenceTemperature><RelaxationTemperature PropType="double" UCat="Temperature" Unt="Celsius">    0</RelaxationTemperature><UnitSystem PropType="int">0</UnitSystem><UseReferenceTemperature PropType="bool">false</UseReferenceTemperature><UseRelaxationTemperature PropType="bool">false</UseRelaxationTemperature></MaterialRep></BodyAttributes><Centroid ObjId="64" Type="DSGePoint3d" Ver="3"><Coordinates PropType="vector&lt;double>" UCat="Length" Unt="mm">-20.32239059978147,1.000000047497351,-6.712913236912678</Coordinates></Centroid><MassMomentOfInertia ObjId="65" Type="MassMomentOfInertia" Ver="2"><Ixx PropType="double" UCat="MomentInertiaMass" Unt="tonne mm^2">6.075013844705717e-05</Ixx><Iyy PropType="double" UCat="MomentInertiaMass" Unt="tonne mm^2">0.000264933137723664</Iyy><Izz PropType="double" UCat="MomentInertiaMass" Unt="tonne mm^2">0.000207097378205888</Izz><CoordinateSystemRep ObjId="66" Type="CoordinateSystemRep" Ver="3"><Caption PropType="string">Undefined</Caption><CoordSystemIndex PropType="unsigned int">0</CoordSystemIndex><IsGlobal PropType="bool">false</IsGlobal><Param1 PropType="double">    1</Param1><Param2 PropType="double">    1</Param2><Singularity1 PropType="int">0</Singularity1><Singularity2 PropType="int">0</Singularity2><SolverCoordNumber PropType="unsigned int">0</SolverCoordNumber><Type PropType="string">Cartesian</Type><DSGePoint3d ObjId="68" Type="DSGePoint3d" Ver="3"><Coordinates PropType="vector&lt;double>" UCat="Length" Unt="mm">-20.32239059978147,1.000000047497351,-6.712913236912678</Coordinates></DSGePoint3d><Matrix3X3 ObjId="67" Type="Matrix3X3" Ver="2"><IsOrthogonal PropType="bool">false</IsOrthogonal><Row0 PropType="vector&lt;double>">0.9033831704926748,-8.121947359035549e-11,0.4288342888233203</Row0><Row1 PropType="vector&lt;double>">1.318236176723994e-10,    1,-8.830395580599751e-11</Row1><Row2 PropType="vector&lt;double>">-0.4288342888233203,1.363027948977277e-10,0.9033831704926748</Row2></Matrix3X3></CoordinateSystemRep></MassMomentOfInertia></PartAttributes></AssemblyAttributes></GeometryAttributes><ServiceRep ObjId="57" Type="ServiceRep" Ver="2"><CoordinateSystemRep ObjId="21" Type="CoordinateSystemRep" Ver="3"><Caption PropType="string">Global Coordinate System</Caption><CoordSystemIndex PropType="unsigned int">0</CoordSystemIndex><IsGlobal PropType="bool">true</IsGlobal><Param1 PropType="double">    1</Param1><Param2 PropType="double">    1</Param2><Singularity1 PropType="int">0</Singularity1><Singularity2 PropType="int">0</Singularity2><SolverCoordNumber PropType="int">0</SolverCoordNumber><Type PropType="string">Cartesian</Type><DSGePoint3d ObjId="70" Type="DSGePoint3d" Ver="3"><Coordinates PropType="vector&lt;double>" UCat="Length" Unt="mm">    0,    0,    0</Coordinates></DSGePoint3d><Matrix3X3 ObjId="69" Type="Matrix3X3" Ver="2"><IsOrthogonal PropType="bool">false</IsOrthogonal><Row0 PropType="vector&lt;double>">    1,    0,    0</Row0><Row1 PropType="vector&lt;double>">    0,    1,    0</Row1><Row2 PropType="vector&lt;double>">    0,    0,    1</Row2></Matrix3X3></CoordinateSystemRep></ServiceRep></EngineeringRep><GeometryRep ObjId="60" Type="GeometryRep" Ver="2"><ActiveAssembly PropType="unsigned int">1</ActiveAssembly><PartsAssembly PropType="string">0000000003390588</PartsAssembly><Units PropType="string">m</Units></GeometryRep><MaterialLibraryRep ObjId="59" Type="MaterialLibraryRep" Ver="2"><FileName PropType="string">MatML.xml</FileName></MaterialLibraryRep><MeshRep ObjId="58" Type="MeshRep" Ver="2"><AssemblyMesh PropType="string">0000000039EC15A8</AssemblyMesh><Configuration PropType="unsigned int">27</Configuration><IndependentMesh PropType="string">IndependentMesh.bin</IndependentMesh><RigidBodyBehavior PropType="string">DimensionallyReduced</RigidBodyBehavior><Units PropType="string">m</Units></MeshRep><SolverRep ObjId="72" Type="SolverRep" Ver="2"><AnalysisType PropType="string">TOpt</AnalysisType><PhysicsType PropType="string">Mechanical</PhysicsType><SolverTargetName PropType="string">ANSYS</SolverTargetName><SolverUnits PropType="int">6</SolverUnits><ProcessControls ObjId="73" Type="ProcessControls" Ver="2"><DistributedSolve PropType="bool">true</DistributedSolve><IsLocal PropType="bool">true</IsLocal><IsRSMSolve PropType="bool">false</IsRSMSolve><ManualMemorySettings PropType="bool">false</ManualMemorySettings><MaxProcessors PropType="int">2</MaxProcessors></ProcessControls><AnalysisSettings CAEType="extObj"><TopologyOptimizationMechanicalSettings version="1.0"><SolverFileControls version="1.0"><SolverEngineType>ANSYS</SolverEngineType><SolverUnits>6</SolverUnits><SolverFilesDirectory>C:\Users\janga\AppData\Local\Temp\WB_janga_13636_2\wbnew_files\dp0\SYS-1\MECH\</SolverFilesDirectory><SolverJobname>file</SolverJobname><ScratchSolverFilesDirectory>C:\Users\janga\AppData\Local\Temp\WB_janga_13636_2\_ProjectScratch\Scr55A6\</ScratchSolverFilesDirectory><AdditionalList></AdditionalList><SaveANSYSDB>false</SaveANSYSDB><ContactSummary>kAnalysisSettingsContactSummaryProgramControlled</ContactSummary><DeleteUnusedFiles>true</DeleteUnusedFiles><ResultFile></ResultFile><MaxNumIntermediateResultFiles>0</MaxNumIntermediateResultFiles></SolverFileControls><TopologyOptimizationControls version="1.0"><MaxNumIterations>500</MaxNumIterations><MassFraction>0.</MassFraction><MinNormalizedDensity>1.e-003</MinNormalizedDensity><ConvergenceAccuracyPercentage>0.1</ConvergenceAccuracyPercentage><PowerLawStiff>3.</PowerLawStiff><MoveLimit>0.</MoveLimit><NonLinearContact>ProgramControlled</NonLinearContact><NonLinearContactFlag>No</NonLinearContactFlag><MaxOuterIterations>100</MaxOuterIterations><OuterConvergenceTolerance>8.</OuterConvergenceTolerance><OptimizationOutputLog>ProgramControlled</OptimizationOutputLog><RegionOfManufacturingConstraint>IncludeExclusion</RegionOfManufacturingConstraint><RegionOfMinMemberSize>ExcludeExclusion</RegionOfMinMemberSize><DensityFilter>ProgramControlled</DensityFilter><ExportDensityFile>Yes</ExportDensityFile></TopologyOptimizationControls><SolverControls version="1.0"><SolverType><ProgramControlled/></SolverType></SolverControls><OutputControls version="1.0"><ResultSetsType>Auto</ResultSetsType><CacheResultsInMemoryType>Never</CacheResultsInMemoryType><StoreModalResult>ProgramControlled</StoreModalResult><ExpandResultFrom>ProgramControlled</ExpandResultFrom><ProgControlledExpansion>Unknown</ProgControlledExpansion><NodalForcesType>No</NodalForcesType><CalculateParticipationFactorResult>ProgramControlled</CalculateParticipationFactorResult><CombineResultFiles>ProgramControlled</CombineResultFiles><ResultFileCompression>ProgramControlled</ResultFileCompression><TimePointsOptions>All</TimePointsOptions><ResultSets></ResultSets></OutputControls></TopologyOptimizationMechanicalSettings></AnalysisSettings></SolverRep></CAERep>